withings_api/__init__.py
withings_api/api.py
withings_api/common.py
withings_api/const.py
withings_api/exceptions.py
withings_api/models/__init__.py
withings_api/models/credentials.py
withings_api/models/notify.py
withings_api/models/response.py
withings_api_cdt-2.7.0.dist-info/LICENSE
withings_api_cdt-2.7.0.dist-info/WHEEL
withings_api_cdt-2.7.0.dist-info/METADATA
withings_api_cdt-2.7.0.dist-info/RECORD
