Metadata-Version: 2.1
Name: withings-api-cdt
Version: 2.7.0
Summary: Codustry Fork of withings_api
Home-page: https://github.com/codustry/python_withings_api
License: MIT
Keywords: withings,api
Author: Nutchanon Ninyawee
Author-email: nutchanon@codustry.com
Requires-Python: >=3.6,<4.0
Classifier: License :: OSI Approved :: MIT License
Classifier: Programming Language :: Python :: 3
Classifier: Programming Language :: Python :: 3.6
Classifier: Programming Language :: Python :: 3.7
Classifier: Programming Language :: Python :: 3.8
Classifier: Programming Language :: Python :: 3.9
Requires-Dist: arrow (>=0.15.2)
Requires-Dist: autoname (>=0.1.2,<0.2.0)
Requires-Dist: pydantic (>=1.7.2,<2.0.0)
Requires-Dist: requests-oauth (>=0.4.1)
Requires-Dist: requests-oauthlib (>=1.2)
Requires-Dist: typing-extensions (>=3.7.4.2)
Project-URL: Repository, https://github.com/codustry/python_withings_api
